ioscmd/__init__.py
ioscmd/__main__.py
ioscmd/command/__init__.py
ioscmd/command/cli.py
ioscmd/command/devices.py
ioscmd/command/install.py
ioscmd/command/pull.py
ioscmd/command/shell.py
ioscmd/command/ssh.py
ioscmd/command/upload.py
ioscmd/exceptions.py
ioscmd/sockets.py
ioscmd/ssh_client.py
ioscmd/utils.py
ioscmd-0.1.6.dist-info/LICENSE
ioscmd-0.1.6.dist-info/METADATA
ioscmd-0.1.6.dist-info/WHEEL
ioscmd-0.1.6.dist-info/entry_points.txt
ioscmd-0.1.6.dist-info/RECORD
